surething/__init__.py
surething/sureThing_pb2.py
surething_proto-1.0.1.dist-info/LICENSE
surething_proto-1.0.1.dist-info/METADATA
surething_proto-1.0.1.dist-info/WHEEL
surething_proto-1.0.1.dist-info/top_level.txt
surething_proto-1.0.1.dist-info/RECORD
