Metadata-Version: 2.1
Name: surething-proto
Version: 1.0.1
Summary: SureThing Protobuf Python classes package
Home-page: UNKNOWN
Author: SureThing
Author-email: miguel.francisco1998@gmail.com
License: UNKNOWN
Platform: UNKNOWN
Classifier: Programming Language :: Python :: 3
Classifier: License :: OSI Approved :: MIT License
Classifier: Operating System :: OS Independent
